{
  "type_description_msg": {
    "type_description": {
      "type_name": "hapthexa_msgs/action/MoveLeg_Feedback",
      "fields": [
        {
          "name": "loadcell1",
          "type": {
            "type_id": 11,
            "capacity": 0,
            "string_capacity": 0,
            "nested_type_name": ""
          },
          "default_value": ""
        },
        {
          "name": "loadcell2",
          "type": {
            "type_id": 11,
            "capacity": 0,
            "string_capacity": 0,
            "nested_type_name": ""
          },
          "default_value": ""
        },
        {
          "name": "piezo",
          "type": {
            "type_id": 11,
            "capacity": 0,
            "string_capacity": 0,
            "nested_type_name": ""
          },
          "default_value": ""
        }
      ]
    },
    "referenced_type_descriptions": []
  },
  "type_hashes": [
    {
      "type_name": "hapthexa_msgs/action/MoveLeg_Feedback",
      "hash_string": "RIHS01_25dc5b43050188a91637d1a23487395f09b27ef8a95420e54f174fd0ba88aacf"
    }
  ]
}